README.md
setup.py
aliblackenlib/__init__.py
aliblackenlib/test.py
aliprojectlib.egg-info/PKG-INFO
aliprojectlib.egg-info/SOURCES.txt
aliprojectlib.egg-info/dependency_links.txt
aliprojectlib.egg-info/top_level.txt